potrace/__init__.py
potrace/__main__.py
potrace/common.py
potrace/io.py
potrace/potrace.py
potrace_py-0.0.1.dist-info/LICENSE.txt
potrace_py-0.0.1.dist-info/METADATA
potrace_py-0.0.1.dist-info/WHEEL
potrace_py-0.0.1.dist-info/top_level.txt
potrace_py-0.0.1.dist-info/RECORD
